models/__init__.py
models/gan.py
models/wgan_gp.py
modules/__init__.py
modules/basemodel.py
modules/dblock.py
modules/gblock.py
modules/losses.py
training/__init__.py
training/logger.py
training/metric_log.py
training/trainer.py
utils/__init__.py
utils/common.py
repro_gan-0.0.1.dist-info/LICENSE
repro_gan-0.0.1.dist-info/METADATA
repro_gan-0.0.1.dist-info/WHEEL
repro_gan-0.0.1.dist-info/top_level.txt
repro_gan-0.0.1.dist-info/RECORD
