Metadata-Version: 2.1
Name: repro-gan
Version: 0.0.1
Summary: PyTorch 1D GAN library that provides you with modules, utilities, and metrics to create GAN models easily
Home-page: https://github.com/joshparksj/repro-gan
Author: Joshua Park
Author-email: joshparksj@gmail.com
License: MIT
Classifier: License :: OSI Approved :: MIT License
Classifier: Programming Language :: Python :: 3.10
Classifier: Operating System :: OS Independent
Requires-Python: >=3.10
License-File: LICENSE
Requires-Dist: numpy (>=1.23.1)
Requires-Dist: scipy (>=1.9.0)
Requires-Dist: torch (>=1.12.1)
Requires-Dist: matplotlib (>=3.5.2)
Requires-Dist: scikit-learn (>=1.1.2)
Requires-Dist: tensorboard (>=2.7.0)
Provides-Extra: dev
Requires-Dist: pytest (>=7.0) ; extra == 'dev'
Requires-Dist: twine (>=4.0.2) ; extra == 'dev'
